alchemylite/BaseAbstract.py
alchemylite/__init__.py
alchemylite/models.py
alchemylite/async_/__init__.py
alchemylite/async_/config.py
alchemylite/async_/crud.py
alchemylite/exceptions/__init__.py
alchemylite/exceptions/exceptions.py
alchemylite/sync/__init__.py
alchemylite/sync/config.py
alchemylite/sync/crud.py
AlchemyLite-1.2.2.dist-info/LICENSE
AlchemyLite-1.2.2.dist-info/METADATA
AlchemyLite-1.2.2.dist-info/WHEEL
AlchemyLite-1.2.2.dist-info/top_level.txt
AlchemyLite-1.2.2.dist-info/RECORD
