Metadata-Version: 2.2
Name: AlchemyLite
Version: 1.2.2
Summary: A library that simplifies CRUD operations with database.
Home-page: https://github.com/Garinelli/AlchemyLite
Author: Yuri Voskanyan
Author-email: yura.voskanyan.2003@mail.ru
Project-URL: Documentation, https://github.com/Garinelli/AlchemyLite
Keywords: AlchemyLite, alchemylite, Alchemy lite, alchemy lite,crud sqlalchemy,python crud
Classifier: Programming Language :: Python :: 3.10
Classifier: License :: OSI Approved :: MIT License
Classifier: Operating System :: OS Independent
Requires-Python: >=3.10
License-File: LICENSE
Requires-Dist: asyncpg>=0.30.0
Requires-Dist: psycopg-pool>=3.2.3
Requires-Dist: SQLAlchemy>=2.0.36
Requires-Dist: psycopg>=3.2.3
Requires-Dist: psycopg2-binary>=2.9.10
Requires-Dist: psycopg-binary==3.2.4
Requires-Dist: aiosqlite==0.21.0
Dynamic: author
Dynamic: author-email
Dynamic: classifier
Dynamic: description
Dynamic: description-content-type
Dynamic: home-page
Dynamic: keywords
Dynamic: project-url
Dynamic: requires-dist
Dynamic: requires-python
Dynamic: summary
